{"_id":{"$oid":"5d5a49fa689ed536147b06b6"},"email":"afsana@gmail.com","house":"585","road":"18","sector":"A","vatRegNo":"1000111213","binNo":{"$numberInt":"1"},"eTin":"101010101010","tds":{"$numberInt":"1"},"sisterConcern":{"$numberInt":"1"},"buyerCode":{"$numberInt":"1001"},"name":"Afsana","mobileNo":"01671592197","buyerId":{"$numberInt":"17"},"__v":{"$numberInt":"0"}}
{"_id":{"$oid":"5d5a4a63689ed536147b06b7"},"email":"arin@gmail.com","house":"354","road":"16","sector":"A","vatRegNo":"10001111214","binNo":{"$numberInt":"2"},"eTin":"101010101011","tds":{"$numberInt":"1"},"sisterConcern":{"$numberInt":"2"},"buyerCode":{"$numberInt":"1002"},"name":"Arin","mobileNo":"01817582003","buyerId":{"$numberInt":"18"},"__v":{"$numberInt":"0"}}
{"_id":{"$oid":"5d5a4abb689ed536147b06b8"},"email":"nila@gmail.com","house":"213","road":"10","sector":"A","vatRegNo":"10001111215","binNo":{"$numberInt":"3"},"eTin":"101010101012","tds":{"$numberInt":"1"},"sisterConcern":{"$numberInt":"3"},"buyerCode":{"$numberInt":"1003"},"name":"Nila","mobileNo":"01817582012","buyerId":{"$numberInt":"19"},"__v":{"$numberInt":"0"}}
{"_id":{"$oid":"5d5a4b79689ed536147b06b9"},"email":"kabir@gmail.com","house":"122","road":"19","sector":"B","vatRegNo":"10010101015","binNo":{"$numberInt":"4"},"eTin":"10101010103","tds":{"$numberInt":"1"},"sisterConcern":{"$numberInt":"4"},"buyerCode":{"$numberInt":"1004"},"name":"kabir","mobileNo":"01719409633","buyerId":{"$numberInt":"20"},"__v":{"$numberInt":"0"}}
{"_id":{"$oid":"5d5bb2399e63c51cd82af0c3"},"email":"tinazakiqu@mailinator.com","house":"Corrupti incididunt","road":"Est magni ratione e","sector":"Quo quo reprehenderi","vatRegNo":"Nulla rerum in fugia","binNo":{"$numberInt":"86"},"eTin":"Tempora velit sit q","tds":{"$numberInt":"1"},"sisterConcern":{"$numberInt":"52"},"buyerCode":{"$numberInt":"57"},"name":"Valentine Everett","mobileNo":"Quidem iusto corrupt","buyerId":{"$numberInt":"21"},"__v":{"$numberInt":"0"}}
{"_id":{"$oid":"5d5bb7d59e63c51cd82af0c6"},"email":"fypanyhu@mailinator.com","house":"Sunt voluptatibus d","road":"Modi corrupti est f","sector":"Et iste impedit acc","vatRegNo":"Laudantium consequu","binNo":{"$numberInt":"95"},"eTin":"Ea est lorem Nam qui","tds":{"$numberInt":"0"},"sisterConcern":{"$numberInt":"97"},"buyerCode":{"$numberInt":"9"},"name":"Amos Adams","mobileNo":"Sed provident est ","buyerId":{"$numberInt":"22"},"__v":{"$numberInt":"0"}}
{"_id":{"$oid":"5d5bb7f09e63c51cd82af0c7"},"email":"talyceba@mailinator.net","house":"Similique quo est ut","road":"Irure debitis aut no","sector":"Iusto natus pariatur","vatRegNo":"Non quis et et sed f","binNo":{"$numberInt":"95"},"eTin":"Aut sit aspernatur ","tds":{"$numberInt":"1"},"sisterConcern":{"$numberInt":"24"},"buyerCode":{"$numberInt":"83"},"name":"Lynn Reed","mobileNo":"Eum optio sunt qui ","buyerId":{"$numberInt":"23"},"__v":{"$numberInt":"0"}}
{"_id":{"$oid":"5d5bb8109e63c51cd82af0c8"},"email":"mevewy@mailinator.com","house":"Consequuntur do aut ","road":"Velit tenetur quia ","sector":"Nostrud culpa et la","vatRegNo":"Enim sint omnis ipsu","binNo":{"$numberInt":"95"},"eTin":"Et qui adipisci volu","tds":{"$numberInt":"1"},"sisterConcern":{"$numberInt":"76"},"buyerCode":{"$numberInt":"57"},"name":"Petra Manning","mobileNo":"Qui non dolor id sit","buyerId":{"$numberInt":"24"},"__v":{"$numberInt":"0"}}
{"_id":{"$oid":"5d5d2ac456ac8b237c3d58ac"},"email":"zytyli@mailinator.com","house":"Quibusdam nisi volup","road":"Quo temporibus ut de","sector":"Et et quia natus lab","vatRegNo":"Fuga Est eu et aute","binNo":{"$numberInt":"26"},"eTin":"Quo maiores tempora ","tds":{"$numberInt":"1"},"sisterConcern":{"$numberInt":"74"},"buyerCode":{"$numberInt":"25"},"name":"Mufutau Doyle","mobileNo":"Quae ipsam modi earu","buyerId":{"$numberInt":"25"},"__v":{"$numberInt":"0"}}
